AUTHORS.rst
CONTRIBUTING.rst
HISTORY.rst
LICENSE
MANIFEST.in
README.rst
setup.py
python_algorithms/__init__.py
python_algorithms.egg-info/PKG-INFO
python_algorithms.egg-info/SOURCES.txt
python_algorithms.egg-info/dependency_links.txt
python_algorithms.egg-info/not-zip-safe
python_algorithms.egg-info/top_level.txt
python_algorithms/basic/__init__.py
python_algorithms/basic/bag.py
python_algorithms/basic/binary_search.py
python_algorithms/basic/knuth_shuffle.py
python_algorithms/basic/queue.py
python_algorithms/basic/stack.py
python_algorithms/basic/union_find.py
tests/__init__.py
tests/basic/__init__.py
tests/basic/test_bag.py
tests/basic/test_binary_search.py
tests/basic/test_knuth_shuffle.py
tests/basic/test_queue.py
tests/basic/test_stack.py
tests/basic/test_union_find.py