Metadata-Version: 1.1
Name: python-algorithms
Version: 0.2.1
Summary: Python Algorithms contains a collection of useful algorithms written in python.
Home-page: https://github.com/mihassan/python_algorithms
Author: Md. Imrul Hassan
Author-email: mihassan@gmail.com
License: BSD
Keywords: python_algorithms
Platform: UNKNOWN
Classifier: Development Status :: 2 - Pre-Alpha
Classifier: Intended Audience :: Developers
Classifier: License :: OSI Approved :: BSD License
Classifier: Natural Language :: English
Classifier: Programming Language :: Python :: 2
Classifier: Programming Language :: Python :: 2.6
Classifier: Programming Language :: Python :: 2.7
Classifier: Programming Language :: Python :: 3
Classifier: Programming Language :: Python :: 3.3
